argparse_to_md/__init__.py
argparse_to_md/__main__.py
argparse_to_md/_version.py
argparse_to_md/formatter.py
argparse_to_md/loader.py
argparse_to_md/markdown_processor.py
argparse_to_md-0.4.0.dist-info/licenses/LICENSE
argparse_to_md-0.4.0.dist-info/METADATA
argparse_to_md-0.4.0.dist-info/WHEEL
argparse_to_md-0.4.0.dist-info/entry_points.txt
argparse_to_md-0.4.0.dist-info/top_level.txt
argparse_to_md-0.4.0.dist-info/RECORD
