Metadata-Version: 2.4
Name: argparse_to_md
Version: 0.4.0
Summary: Pre-commit hook to generate markdown documentation from argparse-based CLI scripts
Author-email: Ivan Grokhotkov <ivan@espressif.com>
License: MIT License
Project-URL: homepage, https://github.com/igrr/argparse_to_md
Project-URL: repository, https://github.com/igrr/argparse_to_md.git
Project-URL: issues, https://github.com/igrr/argparse_to_md/issues
Project-URL: changelog, https://github.com/igrr/argparse_to_md/blob/main/CHANGELOG.md
Classifier: Development Status :: 4 - Beta
Classifier: Environment :: Console
Classifier: Intended Audience :: Developers
Classifier: License :: OSI Approved :: MIT License
Classifier: Programming Language :: Python :: 3 :: Only
Requires-Python: >=3.9
License-File: LICENSE
Provides-Extra: dev
Requires-Dist: pytest; extra == "dev"
Requires-Dist: pre-commit; extra == "dev"
Requires-Dist: commitizen; extra == "dev"
Dynamic: license-file
